pytest_regex.py
pytest_regex-0.2.0.dist-info/LICENSE
pytest_regex-0.2.0.dist-info/METADATA
pytest_regex-0.2.0.dist-info/WHEEL
pytest_regex-0.2.0.dist-info/entry_points.txt
pytest_regex-0.2.0.dist-info/top_level.txt
pytest_regex-0.2.0.dist-info/RECORD
