Metadata-Version: 2.1
Name: pytest-regex
Version: 0.2.0
Summary: Select pytest tests with regular expressions
Home-page: https://github.com/tylerjereddy/pytest-regex
Author: Tyler Reddy
Author-email: Tyler Reddy <tyler.je.reddy@gmail.com>
Maintainer: Tyler Reddy
Maintainer-email: tyler.je.reddy@gmail.com
License: MIT
Project-URL: Homepage, https://github.com/tylerjereddy/pytest-regex
Classifier: Development Status :: 4 - Beta
Classifier: Framework :: Pytest
Classifier: Intended Audience :: Developers
Classifier: Topic :: Software Development :: Testing
Classifier: Programming Language :: Python
Classifier: Programming Language :: Python :: 3.8
Classifier: Programming Language :: Python :: 3.9
Classifier: Programming Language :: Python :: 3.10
Classifier: Programming Language :: Python :: 3.11
Classifier: Programming Language :: Python :: 3 :: Only
Classifier: Programming Language :: Python :: Implementation :: CPython
Classifier: Operating System :: OS Independent
Classifier: License :: OSI Approved :: MIT License
Requires-Python: >=3.8
License-File: LICENSE
Requires-Dist: pytest (>=3.5.0)
